{"title":"Using Custom Fonts","description":"A guide for adding custom fonts to your Chakra project","tags":["fonts"],"author":{"login":"with-heart","avatarUrl":"https://avatars.githubusercontent.com/u/1954752?v=4","githubUrl":"https://github.com/with-heart","websiteUrl":"http://chanchan.io","bio":"Chakra UI core team member. Frontend engineer at VNDLY.","name":"Mark Chandler","twitterUsername":"grow_love"},"slug":"/guides/custom-fonts","editUrl":"https://github.com/chakra-ui/chakra-ui/edit/develop/website/pages/guides/custom-fonts.mdx","__resourcePath":"guides/custom-fonts.mdx"}